{
  "baseline_mean": [
    6.9992017030335285, 
    2.0034965034965033, 
    4.005458515283843, 
    2.8548387096774195, 
    6.349397590361446, 
    3.411764705882353, 
    0.9957264957264957, 
    7.592920353982301, 
    4.581081081081081, 
    1.949579831932773, 
    -0.1103448275862069, 
    -0.3771929824561403, 
    3.14765100671141, 
    1.7314814814814814, 
    1.6033519553072626, 
    -1.6514285714285712
  ], 
  "baseline_stddev": [
    0.02824286969174432, 
    0.0681892889338465, 
    0.10944833591859769, 
    0.35226338173937993, 
    0.4767797334315513, 
    0.5116858176745054, 
    0.32683228726493835, 
    0.5089842068866692, 
    0.49338206117645095, 
    0.2543318647129673, 
    0.3346071578126401, 
    0.5024562628638486, 
    0.5836225557667024, 
    0.5375954950738809, 
    0.793964625060923, 
    0.9062864348763123
  ], 
  "baselines": [
    7.0, 
    2.0, 
    4.0, 
    3.0, 
    6.0, 
    3.0, 
    1.0, 
    8.0, 
    5.0, 
    2.0, 
    -0.0, 
    -0.0, 
    3.0, 
    2.0, 
    2.0, 
    -2.0
  ], 
  "bl_range": [
    -15, 
    -14, 
    -13, 
    -12, 
    -11, 
    -10, 
    -9, 
    -8, 
    -7, 
    -6, 
    -5, 
    -4, 
    -3, 
    -2, 
    -1, 
    0, 
    1, 
    2, 
    3, 
    4, 
    5, 
    6, 
    7, 
    8, 
    9, 
    10, 
    11, 
    12, 
    13, 
    14, 
    15
  ], 
  "ch_error": [
    0.0, 
    0.0, 
    0.0, 
    0.0, 
    0.0, 
    0.0, 
    0.0, 
    0.0, 
    0.0, 
    0.0, 
    0.0, 
    0.0, 
    0.0, 
    0.0, 
    0.0, 
    0.0
  ], 
  "noise_scan_raw": [
    [
      0, 
      0, 
      0, 
      0, 
      0, 
      0, 
      0, 
      0, 
      0, 
      0, 
      0, 
      0, 
      0, 
      0, 
      0, 
      0, 
      0, 
      0, 
      0, 
      0, 
      0, 
      6, 
      7510, 
      0, 
      0, 
      0, 
      0, 
      0, 
      0, 
      0, 
      0
    ], 
    [
      0, 
      0, 
      0, 
      0, 
      0, 
      0, 
      0, 
      0, 
      0, 
      0, 
      0, 
      0, 
      0, 
      0, 
      0, 
      0, 
      1, 
      1708, 
      7, 
      0, 
      0, 
      0, 
      0, 
      0, 
      0, 
      0, 
      0, 
      0, 
      0, 
      0, 
      0
    ], 
    [
      0, 
      0, 
      0, 
      0, 
      0, 
      0, 
      0, 
      0, 
      0, 
      0, 
      0, 
      0, 
      0, 
      0, 
      0, 
      0, 
      0, 
      0, 
      3, 
      905, 
      8, 
      0, 
      0, 
      0, 
      0, 
      0, 
      0, 
      0, 
      0, 
      0, 
      0
    ], 
    [
      0, 
      0, 
      0, 
      0, 
      0, 
      0, 
      0, 
      0, 
      0, 
      0, 
      0, 
      0, 
      0, 
      0, 
      0, 
      0, 
      0, 
      9, 
      53, 
      0, 
      0, 
      0, 
      0, 
      0, 
      0, 
      0, 
      0, 
      0, 
      0, 
      0, 
      0
    ], 
    [
      0, 
      0, 
      0, 
      0, 
      0, 
      0, 
      0, 
      0, 
      0, 
      0, 
      0, 
      0, 
      0, 
      0, 
      0, 
      0, 
      0, 
      0, 
      0, 
      0, 
      0, 
      54, 
      29, 
      0, 
      0, 
      0, 
      0, 
      0, 
      0, 
      0, 
      0
    ], 
    [
      0, 
      0, 
      0, 
      0, 
      0, 
      0, 
      0, 
      0, 
      0, 
      0, 
      0, 
      0, 
      0, 
      0, 
      0, 
      0, 
      0, 
      1, 
      58, 
      43, 
      0, 
      0, 
      0, 
      0, 
      0, 
      0, 
      0, 
      0, 
      0, 
      0, 
      0
    ], 
    [
      0, 
      0, 
      0, 
      0, 
      0, 
      0, 
      0, 
      0, 
      0, 
      0, 
      0, 
      0, 
      0, 
      0, 
      0, 
      13, 
      209, 
      12, 
      0, 
      0, 
      0, 
      0, 
      0, 
      0, 
      0, 
      0, 
      0, 
      0, 
      0, 
      0, 
      0
    ], 
    [
      0, 
      0, 
      0, 
      0, 
      0, 
      0, 
      0, 
      0, 
      0, 
      0, 
      0, 
      0, 
      0, 
      0, 
      0, 
      0, 
      0, 
      0, 
      0, 
      0, 
      0, 
      0, 
      47, 
      65, 
      1, 
      0, 
      0, 
      0, 
      0, 
      0, 
      0
    ], 
    [
      0, 
      0, 
      0, 
      0, 
      0, 
      0, 
      0, 
      0, 
      0, 
      0, 
      0, 
      0, 
      0, 
      0, 
      0, 
      0, 
      0, 
      0, 
      0, 
      31, 
      43, 
      0, 
      0, 
      0, 
      0, 
      0, 
      0, 
      0, 
      0, 
      0, 
      0
    ], 
    [
      0, 
      0, 
      0, 
      0, 
      0, 
      0, 
      0, 
      0, 
      0, 
      0, 
      0, 
      0, 
      0, 
      0, 
      0, 
      0, 
      7, 
      111, 
      1, 
      0, 
      0, 
      0, 
      0, 
      0, 
      0, 
      0, 
      0, 
      0, 
      0, 
      0, 
      0
    ], 
    [
      0, 
      0, 
      0, 
      0, 
      0, 
      0, 
      0, 
      0, 
      0, 
      0, 
      0, 
      0, 
      0, 
      0, 
      17, 
      127, 
      1, 
      0, 
      0, 
      0, 
      0, 
      0, 
      0, 
      0, 
      0, 
      0, 
      0, 
      0, 
      0, 
      0, 
      0
    ], 
    [
      0, 
      0, 
      0, 
      0, 
      0, 
      0, 
      0, 
      0, 
      0, 
      0, 
      0, 
      0, 
      0, 
      0, 
      44, 
      69, 
      1, 
      0, 
      0, 
      0, 
      0, 
      0, 
      0, 
      0, 
      0, 
      0, 
      0, 
      0, 
      0, 
      0, 
      0
    ], 
    [
      0, 
      0, 
      0, 
      0, 
      0, 
      0, 
      0, 
      0, 
      0, 
      0, 
      0, 
      0, 
      0, 
      0, 
      0, 
      0, 
      0, 
      16, 
      95, 
      38, 
      0, 
      0, 
      0, 
      0, 
      0, 
      0, 
      0, 
      0, 
      0, 
      0, 
      0
    ], 
    [
      0, 
      0, 
      0, 
      0, 
      0, 
      0, 
      0, 
      0, 
      0, 
      0, 
      0, 
      0, 
      0, 
      0, 
      0, 
      0, 
      34, 
      69, 
      5, 
      0, 
      0, 
      0, 
      0, 
      0, 
      0, 
      0, 
      0, 
      0, 
      0, 
      0, 
      0
    ], 
    [
      0, 
      0, 
      0, 
      0, 
      0, 
      0, 
      0, 
      0, 
      0, 
      0, 
      0, 
      0, 
      0, 
      0, 
      0, 
      14, 
      64, 
      80, 
      21, 
      0, 
      0, 
      0, 
      0, 
      0, 
      0, 
      0, 
      0, 
      0, 
      0, 
      0, 
      0
    ], 
    [
      0, 
      0, 
      0, 
      0, 
      0, 
      0, 
      0, 
      0, 
      0, 
      0, 
      0, 
      0, 
      33, 
      67, 
      56, 
      19, 
      0, 
      0, 
      0, 
      0, 
      0, 
      0, 
      0, 
      0, 
      0, 
      0, 
      0, 
      0, 
      0, 
      0, 
      0
    ]
  ], 
  "t1_calib_efficiency": [
    0.999, 
    0.999, 
    0.999, 
    0.999, 
    0.999, 
    0.999, 
    0.999, 
    0.999, 
    0.999, 
    0.999, 
    0.999, 
    0.999, 
    0.999, 
    0.999, 
    0.999, 
    0.999
  ]
}